{
    "sourceFile": "src/views/configuration/visitplace/index.vue",
    "activeCommit": 0,
    "commits": [
        {
            "activePatchIndex": 52,
            "patches": [
                {
                    "date": 1637726124721,
                    "content": "Index: \n===================================================================\n--- \n+++ \n"
                },
                {
                    "date": 1637726156488,
                    "content": "Index: \n===================================================================\n--- \n+++ \n@@ -12,9 +12,11 @@\n       <el-tabs type=\"border-card\">\r\n         <div class=\"visitplace-table-container\">\r\n           <el-form :inline=\"true\" class=\"message-form-service\">\r\n             <el-form-item>\r\n-              <span>{{ $t(\"Configuration.VisitPlace.VisitPlace\") }}</span>\r\n+              <span style=\"font-size: 30px\">{{\r\n+                $t(\"Configuration.VisitPlace.VisitPlace\")\r\n+              }}</span>\r\n             </el-form-item>\r\n             <el-form-item style=\"float: right\">\r\n               <el-button\r\n                 v-if=\"RightsCreate\"\r\n"
                },
                {
                    "date": 1637726761950,
                    "content": "Index: \n===================================================================\n--- \n+++ \n@@ -1,630 +1,14 @@\n-<!--\r\n- * @Descripttion: \r\n- * @version: \r\n- * @Author: Bing\r\n- * @Date: 2020-10-29 17:00:55\r\n- * @LastEditors: sueRimn\r\n- * @LastEditTime: 2021-11-22 14:21:35\r\n--->\r\n <template>\r\n-  <div class=\"configuration-visitplace-container light-gray-background\">\r\n-    <div class=\"visit-place\">\r\n-      <el-tabs type=\"border-card\">\r\n-        <div class=\"visitplace-table-container\">\r\n-          <el-form :inline=\"true\" class=\"message-form-service\">\r\n-            <el-form-item>\r\n-              <span style=\"font-size: 30px\">{{\r\n-                $t(\"Configuration.VisitPlace.VisitPlace\")\r\n-              }}</span>\r\n-            </el-form-item>\r\n-            <el-form-item style=\"float: right\">\r\n-              <el-button\r\n-                v-if=\"RightsCreate\"\r\n-                style=\"width: 150px\"\r\n-                type=\"primary\"\r\n-                @click=\"VisitPlaceAddNew\"\r\n-                >{{\r\n-                  $t(\"Configuration.VisitPlace.CreateVisitPlace\")\r\n-                }}</el-button\r\n-              >\r\n-            </el-form-item>\r\n-          </el-form>\r\n-          <el-table\r\n-            ref=\"VisitPlaceTable\"\r\n-            v-loading=\"TableLoading\"\r\n-            :element-loading-text=\"$t('LoadingTip')\"\r\n-            :row-style=\"{ height: '0' }\"\r\n-            :cell-style=\"{ padding: '5px' }\"\r\n-            :data=\"tableData\"\r\n-            style=\"width: 100%; min-height: calc(100vh - 230px)\"\r\n-            class=\"visitplace-table\"\r\n-            :header-cell-style=\"{ background: '#f0f2f5' }\"\r\n-          >\r\n-            <el-table-column\r\n-              :label=\"$t('Configuration.VisitPlace.EnName')\"\r\n-              prop=\"enname\"\r\n-              width=\"220px\"\r\n-              align=\"left\"\r\n-            />\r\n-            <el-table-column\r\n-              :label=\"$t('Configuration.VisitPlace.LocalName')\"\r\n-              prop=\"localname\"\r\n-              width=\"220px\"\r\n-              align=\"left\"\r\n-            />\r\n-            <el-table-column\r\n-              :label=\"$t('Configuration.VisitPlace.BranchName')\"\r\n-              prop=\"branch\"\r\n-              width=\"200px\"\r\n-              align=\"left\"\r\n-            />\r\n-            <el-table-column\r\n-              :label=\"$t('Configuration.VisitPlace.AddressEN')\"\r\n-              prop=\"addr_en\"\r\n-              align=\"left\"\r\n-            />\r\n-            <!-- <el-table-column \r\n-              :label=\"$t('Configuration.VisitPlace.TimerArea')\"\r\n-              prop=\"timezone\"\r\n-              align=\"center\"\r\n-              :index=\"5\"\r\n-            /> -->\r\n-            <el-table-column\r\n-              v-if=\"RightsUpdate || RightsDelete\"\r\n-              align=\"center\"\r\n-              width=\"100px\"\r\n-            >\r\n-              <template slot-scope=\"scope\">\r\n-                <el-tooltip\r\n-                  :open-delay=\"1000\"\r\n-                  class=\"item\"\r\n-                  effect=\"dark\"\r\n-                  :content=\"$t('Modify')\"\r\n-                  placement=\"top-start\"\r\n-                >\r\n-                  <el-button\r\n-                    v-if=\"RightsUpdate\"\r\n-                    size=\"mini\"\r\n-                    class=\"editdeleteBtnSize\"\r\n-                    @click=\"VisitPlaceEdit(scope.row)\"\r\n-                  >\r\n-                    <svg-icon id=\"userEDIT\" icon-class=\"icd-edit\" />\r\n-                  </el-button>\r\n-                </el-tooltip>\r\n-                <el-tooltip\r\n-                  :open-delay=\"1000\"\r\n-                  class=\"item\"\r\n-                  effect=\"dark\"\r\n-                  :content=\"$t('Delete')\"\r\n-                  placement=\"top-start\"\r\n-                >\r\n-                  <el-popconfirm\r\n-                    :title=\"$t('Administrator.Users.TipeDeleteC')\"\r\n-                    :confirm-button-text=\"$t('OK')\"\r\n-                    :cancel-button-text=\"$t('Cancel')\"\r\n-                    icon-color=\"red\"\r\n-                    @onConfirm=\"VisitPlaceDelete(scope.row)\"\r\n-                  >\r\n-                    <el-button\r\n-                      v-if=\"RightsDelete\"\r\n-                      slot=\"reference\"\r\n-                      size=\"mini\"\r\n-                      type=\"danger\"\r\n-                      class=\"editdeleteBtnSize\"\r\n-                    >\r\n-                      <svg-icon id=\"userDELETE\" icon-class=\"icd-delete\" />\r\n-                    </el-button>\r\n-                  </el-popconfirm>\r\n-                </el-tooltip>\r\n-              </template>\r\n-            </el-table-column>\r\n-          </el-table>\r\n-        </div>\r\n-      </el-tabs>\r\n-    </div>\r\n-\r\n-    <!-- update visitplace -->\r\n-    <el-dialog\r\n-      class=\"editvisitplace-dialog\"\r\n-      :title=\"$t('Configuration.VisitPlace.EditVisitPlace')\"\r\n-      :visible.sync=\"Dialog.editDlgVisible\"\r\n-      :close-on-click-modal=\"false\"\r\n-      @opened=\"HandleDialogOpen\"\r\n-      @closed=\"HandleDialogClose\"\r\n-    >\r\n-      <div>\r\n-        <el-form\r\n-          ref=\"Dialog\"\r\n-          v-loading=\"Dialog.DlgLoading\"\r\n-          :model=\"Dialog\"\r\n-          :rules=\"VisitPlacerules\"\r\n-          label-position=\"left\"\r\n-          label-width=\"250px\"\r\n-          destroy-on-close=\"true\"\r\n-          clase=\"create-visitplace-form\"\r\n-        >\r\n-          <el-form-item\r\n-            class=\"icdforminterval\"\r\n-            prop=\"dialogbranch\"\r\n-            :label=\"$t('Configuration.VisitPlace.BranchName')\"\r\n-          >\r\n-            <el-input\r\n-              v-model=\"Dialog.dialogbranch\"\r\n-              v-input-filter:common\r\n-              :placeholder=\"$t('Configuration.VisitPlace.BranchOnlyTip2')\"\r\n-              maxlength=\"16\"\r\n-              :disabled=\"BranchCodeReadOnly\"\r\n-            />\r\n-          </el-form-item>\r\n-          <el-form-item\r\n-            class=\"icdforminterval\"\r\n-            prop=\"dialogenname\"\r\n-            :label=\"$t('Configuration.VisitPlace.EnName')\"\r\n-          >\r\n-            <el-input\r\n-              v-model=\"Dialog.dialogenname\"\r\n-              v-input-filter:common\r\n-              maxlength=\"64\"\r\n-            />\r\n-          </el-form-item>\r\n-          <el-form-item\r\n-            class=\"icdforminterval\"\r\n-            prop=\"dialoglocalname\"\r\n-            :label=\"$t('Configuration.VisitPlace.LocalName')\"\r\n-          >\r\n-            <el-input\r\n-              v-model=\"Dialog.dialoglocalname\"\r\n-              v-input-filter:common\r\n-              maxlength=\"64\"\r\n-            />\r\n-          </el-form-item>\r\n-          <el-form-item\r\n-            class=\"icdforminterval\"\r\n-            :label=\"$t('Management.Visitor.CountryorRegion')\"\r\n-          >\r\n-            <el-select\r\n-              v-model=\"Dialog.dialogNationCode\"\r\n-              :placeholder=\"$t('Configuration.VisitPlace.SelectNationTip')\"\r\n-              class=\"full-width\"\r\n-            >\r\n-              <el-option\r\n-                v-for=\"item in Dialog.dialogNation\"\r\n-                :key=\"item.key\"\r\n-                :label=\"item.label\"\r\n-                :value=\"item.value\"\r\n-              />\r\n-            </el-select>\r\n-          </el-form-item>\r\n-          <el-form-item\r\n-            class=\"icdforminterval\"\r\n-            prop=\"dialogTimezone\"\r\n-            :label=\"$t('Configuration.VisitPlace.TimeZone')\"\r\n-          >\r\n-            <el-select\r\n-              v-model=\"Dialog.dialogZone\"\r\n-              :placeholder=\"$t('Configuration.VisitPlace.SelectTimeZone')\"\r\n-              class=\"full-width\"\r\n-            >\r\n-              <el-option\r\n-                v-for=\"item in Dialog.dialogTimeZone\"\r\n-                :key=\"item.Name\"\r\n-                :label=\"item.Name\"\r\n-                :value=\"item.Name\"\r\n-              />\r\n-            </el-select>\r\n-          </el-form-item>\r\n-          <el-form-item\r\n-            class=\"icdforminterval\"\r\n-            prop=\"dialogAddressEN\"\r\n-            :label=\"$t('Configuration.VisitPlace.AddressEN')\"\r\n-          >\r\n-            <el-input\r\n-              v-model=\"Dialog.dialogAddressEN\"\r\n-              v-input-filter:common\r\n-              maxlength=\"250\"\r\n-            />\r\n-          </el-form-item>\r\n-          <el-form-item\r\n-            class=\"icdforminterval\"\r\n-            prop=\"dialogAddressCN\"\r\n-            :label=\"$t('Configuration.VisitPlace.AddressCN')\"\r\n-          >\r\n-            <el-input\r\n-              v-model=\"Dialog.dialogAddressCN\"\r\n-              v-input-filter:common\r\n-              maxlength=\"250\"\r\n-            />\r\n-          </el-form-item>\r\n-          <el-divider />\r\n-          <el-form-item\r\n-            class=\"icdforminterval\"\r\n-            :label=\"$t('Configuration.VisitPlace.SMSEnable')\"\r\n-          >\r\n-            <el-switch v-model=\"Dialog.dialogMessageEnable\" />\r\n-          </el-form-item>\r\n-          <el-form-item\r\n-            class=\"icdforminterval\"\r\n-            :rules=\"[\r\n-              {\r\n-                required: Dialog.dialogMessageEnable,\r\n-                message: this.$t('Configuration.VisiPlace.TipSMSServiceEmpty'),\r\n-                trigger: 'blur',\r\n-              },\r\n-            ]\"\r\n-            prop=\"dialogMessageService\"\r\n-            :label=\"$t('Configuration.VisitPlace.SMSServiceName')\"\r\n-          >\r\n-            <el-select\r\n-              v-model=\"Dialog.dialogMessageService\"\r\n-              style=\"width: 63%\"\r\n-              :disabled=\"!Dialog.dialogMessageEnable\"\r\n-            >\r\n-              <el-option\r\n-                v-for=\"item in Dialog.dialogSMSService\"\r\n-                :key=\"item.key\"\r\n-                :label=\"item.label\"\r\n-                :value=\"item.value\"\r\n-              />\r\n-            </el-select>\r\n-            <span>\r\n-              <el-button\r\n-                type=\"text\"\r\n-                style=\"margin-left: 2%\"\r\n-                @click=\"CreateMessage(1)\"\r\n-              >\r\n-                {{ $t(\"Configuration.VisitPlace.CreateSMSService\") }}\r\n-              </el-button>\r\n-            </span>\r\n-          </el-form-item>\r\n-          <el-form-item\r\n-            class=\"icdforminterval\"\r\n-            :rules=\"[\r\n-              {\r\n-                required: Dialog.dialogMessageEnable,\r\n-                message: this.$t(\r\n-                  'Configuration.VisiPlace.TipSMSTemplateGroupEmpty'\r\n-                ),\r\n-                trigger: 'blur',\r\n-              },\r\n-            ]\"\r\n-            prop=\"dialogMessageTemplate\"\r\n-            :label=\"$t('Configuration.VisitPlace.SMSTemplateGroupName')\"\r\n-          >\r\n-            <el-select\r\n-              v-model=\"Dialog.dialogMessageTemplate\"\r\n-              style=\"width: 63%\"\r\n-              :disabled=\"!Dialog.dialogMessageEnable\"\r\n-            >\r\n-              <el-option\r\n-                v-for=\"item in Dialog.dialogSMSTemGroup\"\r\n-                :key=\"item.key\"\r\n-                :label=\"item.label\"\r\n-                :value=\"item.value\"\r\n-              />\r\n-            </el-select>\r\n-            <span>\r\n-              <el-button\r\n-                type=\"text\"\r\n-                style=\"margin-left: 2%\"\r\n-                @click=\"CreateMessage(2)\"\r\n-              >\r\n-                {{ $t(\"Configuration.VisitPlace.CreateSMSTemplate\") }}\r\n-              </el-button>\r\n-            </span>\r\n-            <span>\r\n-              <el-button\r\n-                type=\"text\"\r\n-                style=\"margin-left: 65%\"\r\n-                @click=\"CreateMessage(3)\"\r\n-              >\r\n-                {{ $t(\"Configuration.VisitPlace.CreateSMSTempalteGroup\") }}\r\n-              </el-button>\r\n-            </span>\r\n-          </el-form-item>\r\n-          <el-divider />\r\n-          <el-form-item\r\n-            class=\"icdforminterval\"\r\n-            :label=\"$t('Configuration.VisitPlace.EmailEnable')\"\r\n-          >\r\n-            <el-switch v-model=\"Dialog.dialogEmailEnable\" />\r\n-          </el-form-item>\r\n-          <el-form-item\r\n-            class=\"icdforminterval\"\r\n-            :rules=\"[\r\n-              {\r\n-                required: Dialog.dialogEmailEnable,\r\n-                message: $t('Configuration.VisiPlace.TipEmailServiceEmpty'),\r\n-                trigger: 'blur',\r\n-              },\r\n-            ]\"\r\n-            prop=\"dialogEmailService\"\r\n-            :label=\"$t('Configuration.VisitPlace.EmailAccountName')\"\r\n-          >\r\n-            <el-select\r\n-              v-model=\"Dialog.dialogEmailService\"\r\n-              style=\"width: 63%\"\r\n-              :disabled=\"!Dialog.dialogEmailEnable\"\r\n-            >\r\n-              <el-option\r\n-                v-for=\"item in Dialog.dialogEmailAccount\"\r\n-                :key=\"item.key\"\r\n-                :label=\"item.label\"\r\n-                :value=\"item.value\"\r\n-              />\r\n-            </el-select>\r\n-            <span>\r\n-              <el-button\r\n-                type=\"text\"\r\n-                style=\"margin-left: 2%\"\r\n-                @click=\"CreateEmailDialog(1)\"\r\n-              >\r\n-                {{ $t(\"Configuration.VisitPlace.CreateEmailService\") }}\r\n-              </el-button>\r\n-            </span>\r\n-          </el-form-item>\r\n-          <el-form-item\r\n-            class=\"icdforminterval\"\r\n-            :rules=\"[\r\n-              {\r\n-                required: Dialog.dialogEmailEnable,\r\n-                message: $t(\r\n-                  'Configuration.VisiPlace.TipEmailTemplaetGroupEmpty'\r\n-                ),\r\n-                trigger: 'blur',\r\n-              },\r\n-            ]\"\r\n-            prop=\"dialogEmailTemplate\"\r\n-            :label=\"$t('Configuration.VisitPlace.EmailTemplateGroupName')\"\r\n-          >\r\n-            <el-select\r\n-              v-model=\"Dialog.dialogEmailTemplate\"\r\n-              style=\"width: 63%\"\r\n-              :disabled=\"!Dialog.dialogEmailEnable\"\r\n-            >\r\n-              <el-option\r\n-                v-for=\"item in Dialog.dialogEmailTemGroup\"\r\n-                :key=\"item.key\"\r\n-                :label=\"item.label\"\r\n-                :value=\"item.value\"\r\n-              />\r\n-            </el-select>\r\n-            <span>\r\n-              <el-button\r\n-                type=\"text\"\r\n-                style=\"margin-left: 2%\"\r\n-                @click=\"CreateEmailDialog(2)\"\r\n-              >\r\n-                {{ $t(\"Configuration.VisitPlace.CreateEmailTemplate\") }}\r\n-              </el-button>\r\n-            </span>\r\n-            <span>\r\n-              <el-button\r\n-                type=\"text\"\r\n-                style=\"margin-left: 65%\"\r\n-                @click=\"CreateEmailDialog(3)\"\r\n-              >\r\n-                {{ $t(\"Configuration.VisitPlace.CreateEmailTempalteGroup\") }}\r\n-              </el-button>\r\n-            </span>\r\n-          </el-form-item>\r\n-          <el-form-item label-width=\"80%\" class=\"icdforminterval\">\r\n-            <el-button\r\n-              :loading=\"Dialog.dialogSaveLoading\"\r\n-              type=\"primary\"\r\n-              style=\"width: 8rem\"\r\n-              @click=\"DialogClickSubmit\"\r\n-            >\r\n-              {{ $t(\"Configuration.Save\") }}\r\n-            </el-button>\r\n-          </el-form-item>\r\n-        </el-form>\r\n-      </div>\r\n-    </el-dialog>\r\n-\r\n-    <!-- Message Service -->\r\n-    <el-dialog\r\n-      class=\"create-message-service-dialog\"\r\n-      :title=\"$t('Configuration.SMS.EditService')\"\r\n-      :visible=\"Message.SMSServiceVisible\"\r\n-      :close-on-click-modal=\"false\"\r\n-      @close=\"CloseSMSDlg(1)\"\r\n-    >\r\n-      <div>\r\n-        <template>\r\n-          <message-service\r\n-            ref=\"createsms\"\r\n-            class=\"create-message-account\"\r\n-            @formdata=\"CreateSMSService\"\r\n-          />\r\n-        </template>\r\n-      </div>\r\n-    </el-dialog>\r\n-\r\n-    <!-- Message Template -->\r\n-    <el-dialog\r\n-      class=\"create-message-template-dialog\"\r\n-      :title=\"$t('Configuration.SMS.EditTemplate')\"\r\n-      :visible=\"Message.SMSTemplateVisible\"\r\n-      :close-on-click-modal=\"false\"\r\n-      @close=\"CloseSMSDlg(2)\"\r\n-    >\r\n-      <div>\r\n-        <template>\r\n-          <message-template\r\n-            ref=\"createtemplate\"\r\n-            class=\"create-message-template\"\r\n-            @temformdata=\"CreateSMSTemplate\"\r\n-          />\r\n-        </template>\r\n-      </div>\r\n-    </el-dialog>\r\n-\r\n-    <!-- Message Templaet Group -->\r\n-    <el-dialog\r\n-      class=\"create-message-template-group-dialog\"\r\n-      :title=\"$t('Configuration.SMS.EditTemplateGroup')\"\r\n-      :visible=\"Message.SMSTemplateGroupVisible\"\r\n-      :close-on-click-modal=\"false\"\r\n-      @close=\"CloseSMSDlg(3)\"\r\n-    >\r\n-      <div>\r\n-        <template>\r\n-          <message-template-group\r\n-            ref=\"createtemplategroup\"\r\n-            class=\"create-message-template-group\"\r\n-            @temgroupdata=\"CreateSMSTemplateGroup\"\r\n-          />\r\n-        </template>\r\n-      </div>\r\n-    </el-dialog>\r\n-\r\n-    <!-- 新建邮件服务 -->\r\n-    <el-dialog\r\n-      class=\"aemail-service-dialog\"\r\n-      :title=\"$t('Configuration.Email.EditEmailService')\"\r\n-      :visible=\"Email.EmailServiceDlg\"\r\n-      :close-on-click-modal=\"false\"\r\n-      @close=\"CloseEmailDlg(1)\"\r\n-    >\r\n-      <div>\r\n-        <template>\r\n-          <email-account\r\n-            ref=\"emailaccount\"\r\n-            class=\"create-email-account\"\r\n-            @emailservicedata=\"CreateEmailAccount\"\r\n-          />\r\n-        </template>\r\n-      </div>\r\n-    </el-dialog>\r\n-\r\n-    <!-- 新建邮件模板 -->\r\n-    <el-dialog\r\n-      class=\"email-template-dialog\"\r\n-      :title=\"$t('Configuration.Email.EditEmailTemplate')\"\r\n-      :visible=\"Email.EmailTemplaetDlg\"\r\n-      :close-on-click-modal=\"false\"\r\n-      @close=\"CloseEmailDlg(2)\"\r\n-    >\r\n-      <div>\r\n-        <template>\r\n-          <email-template\r\n-            ref=\"emailtemplate\"\r\n-            class=\"create-email-template\"\r\n-            @emailtemplatedata=\"CreateEmailTemplaet\"\r\n-          />\r\n-        </template>\r\n-      </div>\r\n-    </el-dialog>\r\n-\r\n-    <!-- 新建邮件模板组 -->\r\n-    <el-dialog\r\n-      class=\"email-template-dialog\"\r\n-      :title=\"$t('Configuration.Email.EditEmailTemplateGroup')\"\r\n-      :visible=\"Email.EmailTemplateGroupDlg\"\r\n-      :close-on-click-modal=\"false\"\r\n-      @close=\"CloseEmailDlg(3)\"\r\n-    >\r\n-      <div>\r\n-        <template>\r\n-          <email-template-group\r\n-            ref=\"emailtemplategroup\"\r\n-            class=\"create-email-templategroup\"\r\n-            @emailtemplategroupdata=\"CreateEmailTemplaetGroup\"\r\n-          />\r\n-        </template>\r\n-      </div>\r\n-    </el-dialog>\r\n-  </div>\r\n+  <div class=\"configuration-visitplace-container light-gray-background\"></div>\r\n </template>\r\n \r\n <script>\r\n-import { mapGetters } from \"vuex\";\r\n-import i18n from \"@/languages\";\r\n export default {\r\n   name: \"Visitplace\",\r\n   components: {},\r\n   data() {\r\n-    const ValidateAll = (rule, value, callback) => {\r\n-      if (!value) {\r\n-        value = \"\";\r\n-      }\r\n-      if (rule.field === \"dialogbranch\") {\r\n-        if (value.length < 1) {\r\n-          callback(new Error(i18n.t(\"EmptyTip\")));\r\n-        } else if (value.length > 12) {\r\n-          callback(new Error(i18n.t(\"Configuration.VisitPlace.TipBranchLong\")));\r\n-        } else {\r\n-          if (value.search(/[\\W]/g) !== -1) {\r\n-            callback(new Error(i18n.t(\"Configuration.BranchFormatError\")));\r\n-          }\r\n-          callback();\r\n-        }\r\n-      }\r\n-      if (rule.field === \"dialogenname\") {\r\n-        if (value.length < 1) {\r\n-          callback(new Error(i18n.t(\"EmptyTip\")));\r\n-        } else {\r\n-          callback();\r\n-        }\r\n-      }\r\n-      if (rule.field === \"dialogAddressCN\") {\r\n-        callback();\r\n-      }\r\n-      if (rule.field === \"dialogAddressEN\") {\r\n-        callback();\r\n-      }\r\n-    };\r\n-    return {\r\n-      tableData: [],\r\n-      TableLoading: false,\r\n-      BranchCodeReadOnly: false,\r\n-      VisitPlacerules: {\r\n-        dialogbranch: [\r\n-          { required: true, trigger: \"blur\", validator: ValidateAll },\r\n-        ],\r\n-        dialogenname: [\r\n-          { required: true, trigger: \"blur\", validator: ValidateAll },\r\n-        ],\r\n-      },\r\n-      Dialog: {\r\n-        editDlgVisible: false,\r\n-        DlgLoading: false,\r\n-        dialogbranch: \"\",\r\n-        dialoglocalname: \"\",\r\n-        dialogenname: \"\",\r\n-        dialogAddressCN: \"\",\r\n-        dialogAddressEN: \"\",\r\n-        dialogMessageEnable: false,\r\n-        dialogMessageService: \"\",\r\n-        dialogMessageTemplate: \"\",\r\n-        dialogEmailEnable: false,\r\n-        dialogEmailService: \"\",\r\n-        dialogEmailTemplate: \"\",\r\n-        dialogSaveLoading: false,\r\n-        dialogSMSService: [],\r\n-        dialogSMSTemGroup: [],\r\n-        dialogEmailAccount: [],\r\n-        dialogEmailTemGroup: [],\r\n-        dialogNation: [],\r\n-        dialogNationCode: \"\",\r\n-        dialogTimeZone: [],\r\n-        dialogZone: \"\",\r\n-      },\r\n-      Message: {\r\n-        SMSServiceVisible: false,\r\n-        SMSTemplateVisible: false,\r\n-        SMSTemplateGroupVisible: false,\r\n-      },\r\n-      Email: {\r\n-        EmailServiceDlg: false,\r\n-        EmailTemplaetDlg: false,\r\n-        EmailTemplateGroupDlg: false,\r\n-      },\r\n-      RightsCreate: true,\r\n-      RightsUpdate: true,\r\n-      RightsDelete: true,\r\n-    };\r\n+    return {};\r\n   },\r\n   computed: {\r\n     ...mapGetters([\"userrights\", \"language\"]),\r\n   },\r\n"
                },
                {
                    "date": 1637726792439,
                    "content": "Index: \n===================================================================\n--- \n+++ \n@@ -8,83 +8,8 @@\n   components: {},\r\n   data() {\r\n     return {};\r\n   },\r\n-  computed: {\r\n-    ...mapGetters([\"userrights\", \"language\"]),\r\n-  },\r\n-  created() {\r\n-    this.FetchDta();\r\n-  },\r\n-  methods: {\r\n-    FetchDta() {\r\n-      // todo 如果未获取到应不显示\r\n-    },\r\n-    /**\r\n-     * 编辑来访地点\r\n-     */\r\n-    VisitPlaceEdit(row) {},\r\n-    /**\r\n-     * 删除来访地点\r\n-     */\r\n-    VisitPlaceDelete(row) {},\r\n-    /**\r\n-     * 新建来访地点\r\n-     */\r\n-    VisitPlaceAddNew() {},\r\n-    HandleDialogClose() {\r\n-      this.Dialog.dialogbranch = \"\";\r\n-      this.Dialog.dialogenname = \"\";\r\n-      this.Dialog.dialoglocalname = \"\";\r\n-      this.Dialog.dialogSMSService = [];\r\n-      this.Dialog.dialogSMSTemGroup = [];\r\n-      this.Dialog.dialogEmailAccount = [];\r\n-      this.Dialog.dialogEmailTemGroup = [];\r\n-      this.Dialog.dialogEmailService = \"\";\r\n-      this.Dialog.dialogEmailTemplate = \"\";\r\n-      this.Dialog.dialogMessageService = \"\";\r\n-      this.Dialog.dialogMessageTemplate = \"\";\r\n-      this.Dialog.dialogEmailEnable = false;\r\n-      this.Dialog.dialogMessageEnable = false;\r\n-      this.Dialog.dialogNationCode = \"\";\r\n-      this.Dialog.dialogZone = \"\";\r\n-      this.$refs.Dialog.resetFields();\r\n-    },\r\n-    /**\r\n-     * 提交保存\r\n-     */\r\n-    DialogClickSubmit() {},\r\n-    /**\r\n-     * 获取所有数据\r\n-     */\r\n-    GetAllTemplate() {},\r\n-    // 新建SMS\r\n-    CreateMessage(data) {\r\n-      // 新建短信服务 打开对应的dlg\r\n-    },\r\n-    CloseSMSDlg(data) {\r\n-      // 关闭dlg\r\n-    },\r\n-    CreateSMSService(data) {},\r\n-    CreateSMSTemplate(data) {},\r\n-    CreateSMSTemplateGroup(data) {},\r\n-\r\n-    // 邮件\r\n-    CreateEmailDialog(data) {},\r\n-    // 关闭dialog\r\n-    CloseEmailDlg(data) {},\r\n-    CreateEmailAccount(data) {},\r\n-    CreateEmailTemplaet(data) {},\r\n-    CreateEmailTemplaetGroup(data) {},\r\n-    /**\r\n-     * 获取国家/地区\r\n-     */\r\n-    GetNation() {},\r\n-    /**\r\n-     * 获取时区\r\n-     */\r\n-    GetTimeZone() {},\r\n-  },\r\n };\r\n </script>\r\n \r\n <style lang=\"scss\" scoped>\r\n@@ -92,44 +17,6 @@\n   width: 100%;\r\n   padding-top: 3px;\r\n   min-height: calc(100vh - 50px);\r\n }\r\n-.visit-place {\r\n-  .user-configuration-Info {\r\n-    width: 75%;\r\n-    margin-left: 13%;\r\n-    .message-configuration-info,\r\n-    .email-configuration-info {\r\n-      border: 1px solid #dcdfe6;\r\n-      border-spacing: 2px;\r\n-      padding: 4px 8px;\r\n-      .title {\r\n-        text-align: center;\r\n-        color: #99a9bf;\r\n-        font-size: 1rem;\r\n-        width: 100%;\r\n-        border-bottom: 1px solid #dcdfe6;\r\n-        height: 35px;\r\n-        line-height: 35px;\r\n-      }\r\n-      .message-info,\r\n-      .email-info {\r\n-        padding: 1rem 0;\r\n-        height: 8rem;\r\n-        box-sizing: border-box;\r\n-        text-align: left;\r\n-      }\r\n-    }\r\n-    .email-configuration-info {\r\n-      border-left: 0px;\r\n-    }\r\n-  }\r\n-}\r\n-.editvisitplace-dialog {\r\n-  .create-visitplace {\r\n-    padding: 2rem;\r\n-    width: 100%;\r\n-    text-align: left;\r\n-  }\r\n-}\r\n </style>\r\n \r\n"
                },
                {
                    "date": 1637726812630,
                    "content": "Index: \n===================================================================\n--- \n+++ \n@@ -13,10 +13,9 @@\n </script>\r\n \r\n <style lang=\"scss\" scoped>\r\n .configuration-visitplace-container {\r\n-  width: 100%;\r\n-  padding-top: 3px;\r\n+  padding: 10px 5px 0px 5px;\r\n   min-height: calc(100vh - 50px);\r\n }\r\n </style>\r\n \r\n"
                },
                {
                    "date": 1637726850153,
                    "content": "Index: \n===================================================================\n--- \n+++ \n@@ -1,6 +1,12 @@\n <template>\r\n-  <div class=\"configuration-visitplace-container light-gray-background\"></div>\r\n+  <div class=\"configuration-visitplace-container light-gray-background\">\r\n+    <el-row\r\n+      class=\"dashboard-tabs\"\r\n+      style=\"background: #fff; padding: 16px 16px 0; margin-bottom: 32px\"\r\n+    >\r\n+    </el-row>\r\n+  </div>\r\n </template>\r\n \r\n <script>\r\n export default {\r\n"
                },
                {
                    "date": 1637726865751,
                    "content": "Index: \n===================================================================\n--- \n+++ \n@@ -3,8 +3,9 @@\n     <el-row\r\n       class=\"dashboard-tabs\"\r\n       style=\"background: #fff; padding: 16px 16px 0; margin-bottom: 32px\"\r\n     >\r\n+      我是快递类型界面\r\n     </el-row>\r\n   </div>\r\n </template>\r\n \r\n"
                },
                {
                    "date": 1637726943435,
                    "content": "Index: \n===================================================================\n--- \n+++ \n@@ -3,9 +3,12 @@\n     <el-row\r\n       class=\"dashboard-tabs\"\r\n       style=\"background: #fff; padding: 16px 16px 0; margin-bottom: 32px\"\r\n     >\r\n-      我是快递类型界面\r\n+      <div>\r\n+        <div class=\"left\"></div>\r\n+        <div class=\"right\"></div>\r\n+      </div>\r\n     </el-row>\r\n   </div>\r\n </template>\r\n \r\n"
                },
                {
                    "date": 1637727060370,
                    "content": "Index: \n===================================================================\n--- \n+++ \n@@ -3,9 +3,9 @@\n     <el-row\r\n       class=\"dashboard-tabs\"\r\n       style=\"background: #fff; padding: 16px 16px 0; margin-bottom: 32px\"\r\n     >\r\n-      <div>\r\n+      <div class=\"expressType\">\r\n         <div class=\"left\"></div>\r\n         <div class=\"right\"></div>\r\n       </div>\r\n     </el-row>\r\n@@ -25,7 +25,12 @@\n <style lang=\"scss\" scoped>\r\n .configuration-visitplace-container {\r\n   padding: 10px 5px 0px 5px;\r\n   min-height: calc(100vh - 50px);\r\n+  .expressType {\r\n+    width: 400px;\r\n+    height: 400px;\r\n+    background-color: bisque;\r\n+  }\r\n }\r\n </style>\r\n \r\n"
                },
                {
                    "date": 1637727071291,
                    "content": "Index: \n===================================================================\n--- \n+++ \n@@ -4,10 +4,10 @@\n       class=\"dashboard-tabs\"\r\n       style=\"background: #fff; padding: 16px 16px 0; margin-bottom: 32px\"\r\n     >\r\n       <div class=\"expressType\">\r\n-        <div class=\"left\"></div>\r\n-        <div class=\"right\"></div>\r\n+        <div class=\"left\">111111</div>\r\n+        <div class=\"right\">11111111</div>\r\n       </div>\r\n     </el-row>\r\n   </div>\r\n </template>\r\n"
                },
                {
                    "date": 1637727085020,
                    "content": "Index: \n===================================================================\n--- \n+++ \n@@ -26,10 +26,10 @@\n .configuration-visitplace-container {\r\n   padding: 10px 5px 0px 5px;\r\n   min-height: calc(100vh - 50px);\r\n   .expressType {\r\n-    width: 400px;\r\n-    height: 400px;\r\n+    width: 600px;\r\n+    height: 600px;\r\n     background-color: bisque;\r\n   }\r\n }\r\n </style>\r\n"
                },
                {
                    "date": 1637727104427,
                    "content": "Index: \n===================================================================\n--- \n+++ \n@@ -4,10 +4,10 @@\n       class=\"dashboard-tabs\"\r\n       style=\"background: #fff; padding: 16px 16px 0; margin-bottom: 32px\"\r\n     >\r\n       <div class=\"expressType\">\r\n-        <div class=\"left\">111111</div>\r\n-        <div class=\"right\">11111111</div>\r\n+        <div class=\"left\">我是左边</div>\r\n+        <div class=\"right\">我是右边</div>\r\n       </div>\r\n     </el-row>\r\n   </div>\r\n </template>\r\n"
                },
                {
                    "date": 1637727120491,
                    "content": "Index: \n===================================================================\n--- \n+++ \n@@ -29,8 +29,9 @@\n   .expressType {\r\n     width: 600px;\r\n     height: 600px;\r\n     background-color: bisque;\r\n+    display: flex;\r\n   }\r\n }\r\n </style>\r\n \r\n"
                },
                {
                    "date": 1637727156820,
                    "content": "Index: \n===================================================================\n--- \n+++ \n@@ -30,8 +30,14 @@\n     width: 600px;\r\n     height: 600px;\r\n     background-color: bisque;\r\n     display: flex;\r\n+    .left {\r\n+      width: 50%;\r\n+    }\r\n+    .right {\r\n+      width: 50%;\r\n+    }\r\n   }\r\n }\r\n </style>\r\n \r\n"
                },
                {
                    "date": 1637727170900,
                    "content": "Index: \n===================================================================\n--- \n+++ \n@@ -26,9 +26,9 @@\n .configuration-visitplace-container {\r\n   padding: 10px 5px 0px 5px;\r\n   min-height: calc(100vh - 50px);\r\n   .expressType {\r\n-    width: 600px;\r\n+    width: 900px;\r\n     height: 600px;\r\n     background-color: bisque;\r\n     display: flex;\r\n     .left {\r\n"
                },
                {
                    "date": 1637727183038,
                    "content": "Index: \n===================================================================\n--- \n+++ \n@@ -28,9 +28,9 @@\n   min-height: calc(100vh - 50px);\r\n   .expressType {\r\n     width: 900px;\r\n     height: 600px;\r\n-    background-color: bisque;\r\n+    background-color: rgb(197, 195, 193);\r\n     display: flex;\r\n     .left {\r\n       width: 50%;\r\n     }\r\n"
                },
                {
                    "date": 1637727218101,
                    "content": "Index: \n===================================================================\n--- \n+++ \n@@ -4,9 +4,11 @@\n       class=\"dashboard-tabs\"\r\n       style=\"background: #fff; padding: 16px 16px 0; margin-bottom: 32px\"\r\n     >\r\n       <div class=\"expressType\">\r\n-        <div class=\"left\">我是左边</div>\r\n+        <div class=\"left\">\r\n+          <span>快速名称:</span>\r\n+        </div>\r\n         <div class=\"right\">我是右边</div>\r\n       </div>\r\n     </el-row>\r\n   </div>\r\n"
                },
                {
                    "date": 1637727242522,
                    "content": "Index: \n===================================================================\n--- \n+++ \n@@ -6,8 +6,24 @@\n     >\r\n       <div class=\"expressType\">\r\n         <div class=\"left\">\r\n           <span>快速名称:</span>\r\n+          <ul>\r\n+            <li>圆通快递</li>\r\n+            <li>圆通快递</li>\r\n+\r\n+            <li>圆通快递</li>\r\n+\r\n+            <li>圆通快递</li>\r\n+\r\n+            <li>圆通快递</li>\r\n+\r\n+            <li>圆通快递</li>\r\n+\r\n+            <li>圆通快递</li>\r\n+\r\n+            <li>圆通快递</li>\r\n+          </ul>\r\n         </div>\r\n         <div class=\"right\">我是右边</div>\r\n       </div>\r\n     </el-row>\r\n"
                },
                {
                    "date": 1637727249825,
                    "content": "Index: \n===================================================================\n--- \n+++ \n@@ -9,19 +9,13 @@\n           <span>快速名称:</span>\r\n           <ul>\r\n             <li>圆通快递</li>\r\n             <li>圆通快递</li>\r\n-\r\n             <li>圆通快递</li>\r\n-\r\n             <li>圆通快递</li>\r\n-\r\n             <li>圆通快递</li>\r\n-\r\n             <li>圆通快递</li>\r\n-\r\n             <li>圆通快递</li>\r\n-\r\n             <li>圆通快递</li>\r\n           </ul>\r\n         </div>\r\n         <div class=\"right\">我是右边</div>\r\n"
                },
                {
                    "date": 1637727283888,
                    "content": "Index: \n===================================================================\n--- \n+++ \n@@ -44,8 +44,11 @@\n     background-color: rgb(197, 195, 193);\r\n     display: flex;\r\n     .left {\r\n       width: 50%;\r\n+      ul li {\r\n+        list-style: none;\r\n+      }\r\n     }\r\n     .right {\r\n       width: 50%;\r\n     }\r\n"
                },
                {
                    "date": 1637727566022,
                    "content": "Index: \n===================================================================\n--- \n+++ \n@@ -3,24 +3,8 @@\n     <el-row\r\n       class=\"dashboard-tabs\"\r\n       style=\"background: #fff; padding: 16px 16px 0; margin-bottom: 32px\"\r\n     >\r\n-      <div class=\"expressType\">\r\n-        <div class=\"left\">\r\n-          <span>快速名称:</span>\r\n-          <ul>\r\n-            <li>圆通快递</li>\r\n-            <li>圆通快递</li>\r\n-            <li>圆通快递</li>\r\n-            <li>圆通快递</li>\r\n-            <li>圆通快递</li>\r\n-            <li>圆通快递</li>\r\n-            <li>圆通快递</li>\r\n-            <li>圆通快递</li>\r\n-          </ul>\r\n-        </div>\r\n-        <div class=\"right\">我是右边</div>\r\n-      </div>\r\n     </el-row>\r\n   </div>\r\n </template>\r\n \r\n@@ -37,22 +21,7 @@\n <style lang=\"scss\" scoped>\r\n .configuration-visitplace-container {\r\n   padding: 10px 5px 0px 5px;\r\n   min-height: calc(100vh - 50px);\r\n-  .expressType {\r\n-    width: 900px;\r\n-    height: 600px;\r\n-    background-color: rgb(197, 195, 193);\r\n-    display: flex;\r\n-    .left {\r\n-      width: 50%;\r\n-      ul li {\r\n-        list-style: none;\r\n-      }\r\n-    }\r\n-    .right {\r\n-      width: 50%;\r\n-    }\r\n-  }\r\n }\r\n </style>\r\n \r\n"
                },
                {
                    "date": 1637727651244,
                    "content": "Index: \n===================================================================\n--- \n+++ \n@@ -1,11 +1,10 @@\n <template>\r\n   <div class=\"configuration-visitplace-container light-gray-background\">\r\n-    <el-row\r\n+    <div\r\n       class=\"dashboard-tabs\"\r\n       style=\"background: #fff; padding: 16px 16px 0; margin-bottom: 32px\"\r\n-    >\r\n-    </el-row>\r\n+    ></div>\r\n   </div>\r\n </template>\r\n \r\n <script>\r\n"
                },
                {
                    "date": 1637727707104,
                    "content": "Index: \n===================================================================\n--- \n+++ \n@@ -1,8 +1,8 @@\n <template>\r\n   <div class=\"configuration-visitplace-container light-gray-background\">\r\n     <div\r\n-      class=\"dashboard-tabs\"\r\n+      class=\"expressType\"\r\n       style=\"background: #fff; padding: 16px 16px 0; margin-bottom: 32px\"\r\n     ></div>\r\n   </div>\r\n </template>\r\n"
                },
                {
                    "date": 1637727866893,
                    "content": "Index: \n===================================================================\n--- \n+++ \n@@ -2,9 +2,16 @@\n   <div class=\"configuration-visitplace-container light-gray-background\">\r\n     <div\r\n       class=\"expressType\"\r\n       style=\"background: #fff; padding: 16px 16px 0; margin-bottom: 32px\"\r\n-    ></div>\r\n+    >\r\n+    <el-row>\r\n+      <span>快递公司名称</span>\r\n+      <el-input></el-input>\r\n+        <el-button type=\"primary\"确认收件</el-button\r\n+                    >\r\n+    </el-row>\r\n+    </div>\r\n   </div>\r\n </template>\r\n \r\n <script>\r\n"
                },
                {
                    "date": 1637727872248,
                    "content": "Index: \n===================================================================\n--- \n+++ \n@@ -3,14 +3,13 @@\n     <div\r\n       class=\"expressType\"\r\n       style=\"background: #fff; padding: 16px 16px 0; margin-bottom: 32px\"\r\n     >\r\n-    <el-row>\r\n-      <span>快递公司名称</span>\r\n-      <el-input></el-input>\r\n-        <el-button type=\"primary\"确认收件</el-button\r\n-                    >\r\n-    </el-row>\r\n+      <el-row>\r\n+        <span>快递公司名称</span>\r\n+        <el-input></el-input>\r\n+        <el-button type=\"primary\">确认收件</el-button>\r\n+      </el-row>\r\n     </div>\r\n   </div>\r\n </template>\r\n \r\n"
                },
                {
                    "date": 1637727897185,
                    "content": "Index: \n===================================================================\n--- \n+++ \n@@ -6,9 +6,11 @@\n     >\r\n       <el-row>\r\n         <span>快递公司名称</span>\r\n         <el-input></el-input>\r\n-        <el-button type=\"primary\">确认收件</el-button>\r\n+        <el-button type=\"primary\">添加</el-button>\r\n+        <el-button type=\"primary\">修改</el-button>\r\n+        <el-button type=\"primary\">删除</el-button>\r\n       </el-row>\r\n     </div>\r\n   </div>\r\n </template>\r\n"
                },
                {
                    "date": 1637733131465,
                    "content": "Index: \n===================================================================\n--- \n+++ \n@@ -4,13 +4,15 @@\n       class=\"expressType\"\r\n       style=\"background: #fff; padding: 16px 16px 0; margin-bottom: 32px\"\r\n     >\r\n       <el-row>\r\n-        <span>快递公司名称</span>\r\n+        <el-col>111</el-col>\r\n+        <el-col>222</el-col>\r\n+        <!-- <span>快递公司名称</span>\r\n         <el-input></el-input>\r\n         <el-button type=\"primary\">添加</el-button>\r\n         <el-button type=\"primary\">修改</el-button>\r\n-        <el-button type=\"primary\">删除</el-button>\r\n+        <el-button type=\"primary\">删除</el-button> -->\r\n       </el-row>\r\n     </div>\r\n   </div>\r\n </template>\r\n"
                },
                {
                    "date": 1637733153846,
                    "content": "Index: \n===================================================================\n--- \n+++ \n@@ -4,10 +4,10 @@\n       class=\"expressType\"\r\n       style=\"background: #fff; padding: 16px 16px 0; margin-bottom: 32px\"\r\n     >\r\n       <el-row>\r\n-        <el-col>111</el-col>\r\n-        <el-col>222</el-col>\r\n+        <div></div>\r\n+        <div></div>\r\n         <!-- <span>快递公司名称</span>\r\n         <el-input></el-input>\r\n         <el-button type=\"primary\">添加</el-button>\r\n         <el-button type=\"primary\">修改</el-button>\r\n"
                },
                {
                    "date": 1637733159751,
                    "content": "Index: \n===================================================================\n--- \n+++ \n@@ -4,10 +4,10 @@\n       class=\"expressType\"\r\n       style=\"background: #fff; padding: 16px 16px 0; margin-bottom: 32px\"\r\n     >\r\n       <el-row>\r\n-        <div></div>\r\n-        <div></div>\r\n+        <div>111</div>\r\n+        <div>222</div>\r\n         <!-- <span>快递公司名称</span>\r\n         <el-input></el-input>\r\n         <el-button type=\"primary\">添加</el-button>\r\n         <el-button type=\"primary\">修改</el-button>\r\n"
                },
                {
                    "date": 1637733225566,
                    "content": "Index: \n===================================================================\n--- \n+++ \n@@ -3,17 +3,15 @@\n     <div\r\n       class=\"expressType\"\r\n       style=\"background: #fff; padding: 16px 16px 0; margin-bottom: 32px\"\r\n     >\r\n-      <el-row>\r\n-        <div>111</div>\r\n-        <div>222</div>\r\n-        <!-- <span>快递公司名称</span>\r\n+      <div class=\"left\"></div>\r\n+      <div class=\"right\">222</div>\r\n+      <!-- <span>快递公司名称</span>\r\n         <el-input></el-input>\r\n         <el-button type=\"primary\">添加</el-button>\r\n         <el-button type=\"primary\">修改</el-button>\r\n         <el-button type=\"primary\">删除</el-button> -->\r\n-      </el-row>\r\n     </div>\r\n   </div>\r\n </template>\r\n \r\n"
                },
                {
                    "date": 1637733247323,
                    "content": "Index: \n===================================================================\n--- \n+++ \n@@ -28,7 +28,10 @@\n <style lang=\"scss\" scoped>\r\n .configuration-visitplace-container {\r\n   padding: 10px 5px 0px 5px;\r\n   min-height: calc(100vh - 50px);\r\n+  .expressType {\r\n+    display: flex;\r\n+  }\r\n }\r\n </style>\r\n \r\n"
                },
                {
                    "date": 1637733376473,
                    "content": "Index: \n===================================================================\n--- \n+++ \n@@ -3,9 +3,15 @@\n     <div\r\n       class=\"expressType\"\r\n       style=\"background: #fff; padding: 16px 16px 0; margin-bottom: 32px\"\r\n     >\r\n-      <div class=\"left\"></div>\r\n+      <div class=\"left\">\r\n+        <el-tree\r\n+          :data=\"data\"\r\n+          :props=\"defaultProps\"\r\n+          @node-click=\"handleNodeClick\"\r\n+        ></el-tree>\r\n+      </div>\r\n       <div class=\"right\">222</div>\r\n       <!-- <span>快递公司名称</span>\r\n         <el-input></el-input>\r\n         <el-button type=\"primary\">添加</el-button>\r\n@@ -19,10 +25,78 @@\n export default {\r\n   name: \"Visitplace\",\r\n   components: {},\r\n   data() {\r\n-    return {};\r\n+    return {\r\n+      //节点\r\n+      data: [\r\n+        {\r\n+          label: \"一级 1\",\r\n+          children: [\r\n+            {\r\n+              label: \"二级 1-1\",\r\n+              children: [\r\n+                {\r\n+                  label: \"三级 1-1-1\",\r\n+                },\r\n+              ],\r\n+            },\r\n+          ],\r\n+        },\r\n+        {\r\n+          label: \"一级 2\",\r\n+          children: [\r\n+            {\r\n+              label: \"二级 2-1\",\r\n+              children: [\r\n+                {\r\n+                  label: \"三级 2-1-1\",\r\n+                },\r\n+              ],\r\n+            },\r\n+            {\r\n+              label: \"二级 2-2\",\r\n+              children: [\r\n+                {\r\n+                  label: \"三级 2-2-1\",\r\n+                },\r\n+              ],\r\n+            },\r\n+          ],\r\n+        },\r\n+        {\r\n+          label: \"一级 3\",\r\n+          children: [\r\n+            {\r\n+              label: \"二级 3-1\",\r\n+              children: [\r\n+                {\r\n+                  label: \"三级 3-1-1\",\r\n+                },\r\n+              ],\r\n+            },\r\n+            {\r\n+              label: \"二级 3-2\",\r\n+              children: [\r\n+                {\r\n+                  label: \"三级 3-2-1\",\r\n+                },\r\n+              ],\r\n+            },\r\n+          ],\r\n+        },\r\n+      ],\r\n+      defaultProps: {\r\n+        children: \"children\",\r\n+        label: \"label\",\r\n+      },\r\n+    };\r\n   },\r\n+  methods: {\r\n+    handleNodeClick(data) {\r\n+      console.log(data);\r\n+    },\r\n+  },\r\n };\r\n </script>\r\n \r\n <style lang=\"scss\" scoped>\r\n"
                },
                {
                    "date": 1637733501434,
                    "content": "Index: \n===================================================================\n--- \n+++ \n@@ -4,13 +4,9 @@\n       class=\"expressType\"\r\n       style=\"background: #fff; padding: 16px 16px 0; margin-bottom: 32px\"\r\n     >\r\n       <div class=\"left\">\r\n-        <el-tree\r\n-          :data=\"data\"\r\n-          :props=\"defaultProps\"\r\n-          @node-click=\"handleNodeClick\"\r\n-        ></el-tree>\r\n+        <span style=\"font-size: 20px\">快递名称:</span>\r\n       </div>\r\n       <div class=\"right\">222</div>\r\n       <!-- <span>快递公司名称</span>\r\n         <el-input></el-input>\r\n@@ -25,78 +21,10 @@\n export default {\r\n   name: \"Visitplace\",\r\n   components: {},\r\n   data() {\r\n-    return {\r\n-      //节点\r\n-      data: [\r\n-        {\r\n-          label: \"一级 1\",\r\n-          children: [\r\n-            {\r\n-              label: \"二级 1-1\",\r\n-              children: [\r\n-                {\r\n-                  label: \"三级 1-1-1\",\r\n-                },\r\n-              ],\r\n-            },\r\n-          ],\r\n-        },\r\n-        {\r\n-          label: \"一级 2\",\r\n-          children: [\r\n-            {\r\n-              label: \"二级 2-1\",\r\n-              children: [\r\n-                {\r\n-                  label: \"三级 2-1-1\",\r\n-                },\r\n-              ],\r\n-            },\r\n-            {\r\n-              label: \"二级 2-2\",\r\n-              children: [\r\n-                {\r\n-                  label: \"三级 2-2-1\",\r\n-                },\r\n-              ],\r\n-            },\r\n-          ],\r\n-        },\r\n-        {\r\n-          label: \"一级 3\",\r\n-          children: [\r\n-            {\r\n-              label: \"二级 3-1\",\r\n-              children: [\r\n-                {\r\n-                  label: \"三级 3-1-1\",\r\n-                },\r\n-              ],\r\n-            },\r\n-            {\r\n-              label: \"二级 3-2\",\r\n-              children: [\r\n-                {\r\n-                  label: \"三级 3-2-1\",\r\n-                },\r\n-              ],\r\n-            },\r\n-          ],\r\n-        },\r\n-      ],\r\n-      defaultProps: {\r\n-        children: \"children\",\r\n-        label: \"label\",\r\n-      },\r\n-    };\r\n+    return {};\r\n   },\r\n-  methods: {\r\n-    handleNodeClick(data) {\r\n-      console.log(data);\r\n-    },\r\n-  },\r\n };\r\n </script>\r\n \r\n <style lang=\"scss\" scoped>\r\n"
                },
                {
                    "date": 1637733611862,
                    "content": "Index: \n===================================================================\n--- \n+++ \n@@ -5,8 +5,19 @@\n       style=\"background: #fff; padding: 16px 16px 0; margin-bottom: 32px\"\r\n     >\r\n       <div class=\"left\">\r\n         <span style=\"font-size: 20px\">快递名称:</span>\r\n+        <ul>\r\n+          <li>圆通快递</li>\r\n+          <li>圆通快递</li>\r\n+          <li>圆通快递</li>\r\n+          <li>圆通快递</li>\r\n+          <li>圆通快递</li>\r\n+          <li>圆通快递</li>\r\n+          <li>圆通快递</li>\r\n+          <li>圆通快递</li>\r\n+          <li>圆通快递</li>\r\n+        </ul>\r\n       </div>\r\n       <div class=\"right\">222</div>\r\n       <!-- <span>快递公司名称</span>\r\n         <el-input></el-input>\r\n@@ -32,8 +43,14 @@\n   padding: 10px 5px 0px 5px;\r\n   min-height: calc(100vh - 50px);\r\n   .expressType {\r\n     display: flex;\r\n+    .left {\r\n+      ul li {\r\n+        list-style: none;\r\n+        font-size: 16px;\r\n+      }\r\n+    }\r\n   }\r\n }\r\n </style>\r\n \r\n"
                },
                {
                    "date": 1637733645607,
                    "content": "Index: \n===================================================================\n--- \n+++ \n@@ -46,9 +46,9 @@\n     display: flex;\r\n     .left {\r\n       ul li {\r\n         list-style: none;\r\n-        font-size: 16px;\r\n+        font-size: 20px;\r\n       }\r\n     }\r\n   }\r\n }\r\n"
                },
                {
                    "date": 1637733669065,
                    "content": "Index: \n===================================================================\n--- \n+++ \n@@ -47,8 +47,9 @@\n     .left {\r\n       ul li {\r\n         list-style: none;\r\n         font-size: 20px;\r\n+        line-height: 20px;\r\n       }\r\n     }\r\n   }\r\n }\r\n"
                },
                {
                    "date": 1637733676344,
                    "content": "Index: \n===================================================================\n--- \n+++ \n@@ -47,9 +47,9 @@\n     .left {\r\n       ul li {\r\n         list-style: none;\r\n         font-size: 20px;\r\n-        line-height: 20px;\r\n+        line-height: 30px;\r\n       }\r\n     }\r\n   }\r\n }\r\n"
                },
                {
                    "date": 1637733719404,
                    "content": "Index: \n===================================================================\n--- \n+++ \n@@ -44,8 +44,10 @@\n   min-height: calc(100vh - 50px);\r\n   .expressType {\r\n     display: flex;\r\n     .left {\r\n+      margin-right: 20px;\r\n+      background-color: blueviolet;\r\n       ul li {\r\n         list-style: none;\r\n         font-size: 20px;\r\n         line-height: 30px;\r\n"
                },
                {
                    "date": 1637733729078,
                    "content": "Index: \n===================================================================\n--- \n+++ \n@@ -45,9 +45,8 @@\n   .expressType {\r\n     display: flex;\r\n     .left {\r\n       margin-right: 20px;\r\n-      background-color: blueviolet;\r\n       ul li {\r\n         list-style: none;\r\n         font-size: 20px;\r\n         line-height: 30px;\r\n"
                },
                {
                    "date": 1637733773517,
                    "content": "Index: \n===================================================================\n--- \n+++ \n@@ -17,10 +17,12 @@\n           <li>圆通快递</li>\r\n           <li>圆通快递</li>\r\n         </ul>\r\n       </div>\r\n-      <div class=\"right\">222</div>\r\n-      <!-- <span>快递公司名称</span>\r\n+      <div class=\"right\">\r\n+        <span style=\"font-size: 20px\">快递公司名称:</span>\r\n+      </div>\r\n+      <!-- \r\n         <el-input></el-input>\r\n         <el-button type=\"primary\">添加</el-button>\r\n         <el-button type=\"primary\">修改</el-button>\r\n         <el-button type=\"primary\">删除</el-button> -->\r\n"
                },
                {
                    "date": 1637733792598,
                    "content": "Index: \n===================================================================\n--- \n+++ \n@@ -19,14 +19,13 @@\n         </ul>\r\n       </div>\r\n       <div class=\"right\">\r\n         <span style=\"font-size: 20px\">快递公司名称:</span>\r\n-      </div>\r\n-      <!-- \r\n         <el-input></el-input>\r\n         <el-button type=\"primary\">添加</el-button>\r\n         <el-button type=\"primary\">修改</el-button>\r\n-        <el-button type=\"primary\">删除</el-button> -->\r\n+        <el-button type=\"primary\">删除</el-button>\r\n+      </div>\r\n     </div>\r\n   </div>\r\n </template>\r\n \r\n"
                },
                {
                    "date": 1637737739544,
                    "content": "Index: \n===================================================================\n--- \n+++ \n@@ -20,11 +20,13 @@\n       </div>\r\n       <div class=\"right\">\r\n         <span style=\"font-size: 20px\">快递公司名称:</span>\r\n         <el-input></el-input>\r\n-        <el-button type=\"primary\">添加</el-button>\r\n-        <el-button type=\"primary\">修改</el-button>\r\n-        <el-button type=\"primary\">删除</el-button>\r\n+        <div>\r\n+          <el-button type=\"primary\">添加</el-button>\r\n+          <el-button type=\"primary\">修改</el-button>\r\n+          <el-button type=\"primary\">删除</el-button>\r\n+        </div>\r\n       </div>\r\n     </div>\r\n   </div>\r\n </template>\r\n"
                },
                {
                    "date": 1637737764504,
                    "content": "Index: \n===================================================================\n--- \n+++ \n@@ -20,9 +20,9 @@\n       </div>\r\n       <div class=\"right\">\r\n         <span style=\"font-size: 20px\">快递公司名称:</span>\r\n         <el-input></el-input>\r\n-        <div>\r\n+        <div class=\"btns\">\r\n           <el-button type=\"primary\">添加</el-button>\r\n           <el-button type=\"primary\">修改</el-button>\r\n           <el-button type=\"primary\">删除</el-button>\r\n         </div>\r\n@@ -54,8 +54,15 @@\n         font-size: 20px;\r\n         line-height: 30px;\r\n       }\r\n     }\r\n+    .right {\r\n+      .btns {\r\n+        display: flex;\r\n+        justify-content: space-between;\r\n+        margin-bottom: 50px;\r\n+      }\r\n+    }\r\n   }\r\n }\r\n </style>\r\n \r\n"
                },
                {
                    "date": 1637737781697,
                    "content": "Index: \n===================================================================\n--- \n+++ \n@@ -19,9 +19,9 @@\n         </ul>\r\n       </div>\r\n       <div class=\"right\">\r\n         <span style=\"font-size: 20px\">快递公司名称:</span>\r\n-        <el-input></el-input>\r\n+        <el-input style=\"margin-bottom: 20px\"></el-input>\r\n         <div class=\"btns\">\r\n           <el-button type=\"primary\">添加</el-button>\r\n           <el-button type=\"primary\">修改</el-button>\r\n           <el-button type=\"primary\">删除</el-button>\r\n"
                },
                {
                    "date": 1637737800300,
                    "content": "Index: \n===================================================================\n--- \n+++ \n@@ -18,9 +18,9 @@\n           <li>圆通快递</li>\r\n         </ul>\r\n       </div>\r\n       <div class=\"right\">\r\n-        <span style=\"font-size: 20px\">快递公司名称:</span>\r\n+        <span style=\"font-size: 20px\">快递公司名称</span>\r\n         <el-input style=\"margin-bottom: 20px\"></el-input>\r\n         <div class=\"btns\">\r\n           <el-button type=\"primary\">添加</el-button>\r\n           <el-button type=\"primary\">修改</el-button>\r\n"
                },
                {
                    "date": 1637737818230,
                    "content": "Index: \n===================================================================\n--- \n+++ \n@@ -21,11 +21,11 @@\n       <div class=\"right\">\r\n         <span style=\"font-size: 20px\">快递公司名称</span>\r\n         <el-input style=\"margin-bottom: 20px\"></el-input>\r\n         <div class=\"btns\">\r\n-          <el-button type=\"primary\">添加</el-button>\r\n-          <el-button type=\"primary\">修改</el-button>\r\n-          <el-button type=\"primary\">删除</el-button>\r\n+          <el-button type=\"primary\" style=\"width: 100%\">添加</el-button>\r\n+          <el-button type=\"primary\" style=\"width: 100%\">修改</el-button>\r\n+          <el-button type=\"primary\" style=\"width: 100%\">删除</el-button>\r\n         </div>\r\n       </div>\r\n     </div>\r\n   </div>\r\n"
                },
                {
                    "date": 1637738366915,
                    "content": "Index: \n===================================================================\n--- \n+++ \n@@ -20,8 +20,10 @@\n       </div>\r\n       <div class=\"right\">\r\n         <span style=\"font-size: 20px\">快递公司名称</span>\r\n         <el-input style=\"margin-bottom: 20px\"></el-input>\r\n+        <span style=\"font-size: 20px\">快递公司名称</span>\r\n+        <el-input style=\"margin-bottom: 20px\"></el-input>\r\n         <div class=\"btns\">\r\n           <el-button type=\"primary\" style=\"width: 100%\">添加</el-button>\r\n           <el-button type=\"primary\" style=\"width: 100%\">修改</el-button>\r\n           <el-button type=\"primary\" style=\"width: 100%\">删除</el-button>\r\n"
                },
                {
                    "date": 1637738378372,
                    "content": "Index: \n===================================================================\n--- \n+++ \n@@ -20,10 +20,9 @@\n       </div>\r\n       <div class=\"right\">\r\n         <span style=\"font-size: 20px\">快递公司名称</span>\r\n         <el-input style=\"margin-bottom: 20px\"></el-input>\r\n-        <span style=\"font-size: 20px\">快递公司名称</span>\r\n-        <el-input style=\"margin-bottom: 20px\"></el-input>\r\n+\r\n         <div class=\"btns\">\r\n           <el-button type=\"primary\" style=\"width: 100%\">添加</el-button>\r\n           <el-button type=\"primary\" style=\"width: 100%\">修改</el-button>\r\n           <el-button type=\"primary\" style=\"width: 100%\">删除</el-button>\r\n"
                },
                {
                    "date": 1637738416513,
                    "content": "Index: \n===================================================================\n--- \n+++ \n@@ -20,9 +20,8 @@\n       </div>\r\n       <div class=\"right\">\r\n         <span style=\"font-size: 20px\">快递公司名称</span>\r\n         <el-input style=\"margin-bottom: 20px\"></el-input>\r\n-\r\n         <div class=\"btns\">\r\n           <el-button type=\"primary\" style=\"width: 100%\">添加</el-button>\r\n           <el-button type=\"primary\" style=\"width: 100%\">修改</el-button>\r\n           <el-button type=\"primary\" style=\"width: 100%\">删除</el-button>\r\n"
                },
                {
                    "date": 1637738455425,
                    "content": "Index: \n===================================================================\n--- \n+++ \n@@ -46,8 +46,9 @@\n   padding: 10px 5px 0px 5px;\r\n   min-height: calc(100vh - 50px);\r\n   .expressType {\r\n     display: flex;\r\n+    width: 100%;\r\n     .left {\r\n       margin-right: 20px;\r\n       ul li {\r\n         list-style: none;\r\n"
                },
                {
                    "date": 1637738473691,
                    "content": "Index: \n===================================================================\n--- \n+++ \n@@ -48,8 +48,9 @@\n   .expressType {\r\n     display: flex;\r\n     width: 100%;\r\n     .left {\r\n+      width: 30%;\r\n       margin-right: 20px;\r\n       ul li {\r\n         list-style: none;\r\n         font-size: 20px;\r\n"
                },
                {
                    "date": 1637738487788,
                    "content": "Index: \n===================================================================\n--- \n+++ \n@@ -48,9 +48,9 @@\n   .expressType {\r\n     display: flex;\r\n     width: 100%;\r\n     .left {\r\n-      width: 30%;\r\n+      width: 20%;\r\n       margin-right: 20px;\r\n       ul li {\r\n         list-style: none;\r\n         font-size: 20px;\r\n"
                },
                {
                    "date": 1637738797934,
                    "content": "Index: \n===================================================================\n--- \n+++ \n@@ -32,9 +32,10 @@\n </template>\r\n \r\n <script>\r\n export default {\r\n-  name: \"Visitplace\",\r\n+  name: \"expressType\",\r\n+  // name: \"Visitplace\",\r\n   components: {},\r\n   data() {\r\n     return {};\r\n   },\r\n"
                }
            ],
            "date": 1637726124721,
            "name": "Commit-0",
            "content": "<!--\r\n * @Descripttion: \r\n * @version: \r\n * @Author: Bing\r\n * @Date: 2020-10-29 17:00:55\r\n * @LastEditors: sueRimn\r\n * @LastEditTime: 2021-11-22 14:21:35\r\n-->\r\n<template>\r\n  <div class=\"configuration-visitplace-container light-gray-background\">\r\n    <div class=\"visit-place\">\r\n      <el-tabs type=\"border-card\">\r\n        <div class=\"visitplace-table-container\">\r\n          <el-form :inline=\"true\" class=\"message-form-service\">\r\n            <el-form-item>\r\n              <span>{{ $t(\"Configuration.VisitPlace.VisitPlace\") }}</span>\r\n            </el-form-item>\r\n            <el-form-item style=\"float: right\">\r\n              <el-button\r\n                v-if=\"RightsCreate\"\r\n                style=\"width: 150px\"\r\n                type=\"primary\"\r\n                @click=\"VisitPlaceAddNew\"\r\n                >{{\r\n                  $t(\"Configuration.VisitPlace.CreateVisitPlace\")\r\n                }}</el-button\r\n              >\r\n            </el-form-item>\r\n          </el-form>\r\n          <el-table\r\n            ref=\"VisitPlaceTable\"\r\n            v-loading=\"TableLoading\"\r\n            :element-loading-text=\"$t('LoadingTip')\"\r\n            :row-style=\"{ height: '0' }\"\r\n            :cell-style=\"{ padding: '5px' }\"\r\n            :data=\"tableData\"\r\n            style=\"width: 100%; min-height: calc(100vh - 230px)\"\r\n            class=\"visitplace-table\"\r\n            :header-cell-style=\"{ background: '#f0f2f5' }\"\r\n          >\r\n            <el-table-column\r\n              :label=\"$t('Configuration.VisitPlace.EnName')\"\r\n              prop=\"enname\"\r\n              width=\"220px\"\r\n              align=\"left\"\r\n            />\r\n            <el-table-column\r\n              :label=\"$t('Configuration.VisitPlace.LocalName')\"\r\n              prop=\"localname\"\r\n              width=\"220px\"\r\n              align=\"left\"\r\n            />\r\n            <el-table-column\r\n              :label=\"$t('Configuration.VisitPlace.BranchName')\"\r\n              prop=\"branch\"\r\n              width=\"200px\"\r\n              align=\"left\"\r\n            />\r\n            <el-table-column\r\n              :label=\"$t('Configuration.VisitPlace.AddressEN')\"\r\n              prop=\"addr_en\"\r\n              align=\"left\"\r\n            />\r\n            <!-- <el-table-column \r\n              :label=\"$t('Configuration.VisitPlace.TimerArea')\"\r\n              prop=\"timezone\"\r\n              align=\"center\"\r\n              :index=\"5\"\r\n            /> -->\r\n            <el-table-column\r\n              v-if=\"RightsUpdate || RightsDelete\"\r\n              align=\"center\"\r\n              width=\"100px\"\r\n            >\r\n              <template slot-scope=\"scope\">\r\n                <el-tooltip\r\n                  :open-delay=\"1000\"\r\n                  class=\"item\"\r\n                  effect=\"dark\"\r\n                  :content=\"$t('Modify')\"\r\n                  placement=\"top-start\"\r\n                >\r\n                  <el-button\r\n                    v-if=\"RightsUpdate\"\r\n                    size=\"mini\"\r\n                    class=\"editdeleteBtnSize\"\r\n                    @click=\"VisitPlaceEdit(scope.row)\"\r\n                  >\r\n                    <svg-icon id=\"userEDIT\" icon-class=\"icd-edit\" />\r\n                  </el-button>\r\n                </el-tooltip>\r\n                <el-tooltip\r\n                  :open-delay=\"1000\"\r\n                  class=\"item\"\r\n                  effect=\"dark\"\r\n                  :content=\"$t('Delete')\"\r\n                  placement=\"top-start\"\r\n                >\r\n                  <el-popconfirm\r\n                    :title=\"$t('Administrator.Users.TipeDeleteC')\"\r\n                    :confirm-button-text=\"$t('OK')\"\r\n                    :cancel-button-text=\"$t('Cancel')\"\r\n                    icon-color=\"red\"\r\n                    @onConfirm=\"VisitPlaceDelete(scope.row)\"\r\n                  >\r\n                    <el-button\r\n                      v-if=\"RightsDelete\"\r\n                      slot=\"reference\"\r\n                      size=\"mini\"\r\n                      type=\"danger\"\r\n                      class=\"editdeleteBtnSize\"\r\n                    >\r\n                      <svg-icon id=\"userDELETE\" icon-class=\"icd-delete\" />\r\n                    </el-button>\r\n                  </el-popconfirm>\r\n                </el-tooltip>\r\n              </template>\r\n            </el-table-column>\r\n          </el-table>\r\n        </div>\r\n      </el-tabs>\r\n    </div>\r\n\r\n    <!-- update visitplace -->\r\n    <el-dialog\r\n      class=\"editvisitplace-dialog\"\r\n      :title=\"$t('Configuration.VisitPlace.EditVisitPlace')\"\r\n      :visible.sync=\"Dialog.editDlgVisible\"\r\n      :close-on-click-modal=\"false\"\r\n      @opened=\"HandleDialogOpen\"\r\n      @closed=\"HandleDialogClose\"\r\n    >\r\n      <div>\r\n        <el-form\r\n          ref=\"Dialog\"\r\n          v-loading=\"Dialog.DlgLoading\"\r\n          :model=\"Dialog\"\r\n          :rules=\"VisitPlacerules\"\r\n          label-position=\"left\"\r\n          label-width=\"250px\"\r\n          destroy-on-close=\"true\"\r\n          clase=\"create-visitplace-form\"\r\n        >\r\n          <el-form-item\r\n            class=\"icdforminterval\"\r\n            prop=\"dialogbranch\"\r\n            :label=\"$t('Configuration.VisitPlace.BranchName')\"\r\n          >\r\n            <el-input\r\n              v-model=\"Dialog.dialogbranch\"\r\n              v-input-filter:common\r\n              :placeholder=\"$t('Configuration.VisitPlace.BranchOnlyTip2')\"\r\n              maxlength=\"16\"\r\n              :disabled=\"BranchCodeReadOnly\"\r\n            />\r\n          </el-form-item>\r\n          <el-form-item\r\n            class=\"icdforminterval\"\r\n            prop=\"dialogenname\"\r\n            :label=\"$t('Configuration.VisitPlace.EnName')\"\r\n          >\r\n            <el-input\r\n              v-model=\"Dialog.dialogenname\"\r\n              v-input-filter:common\r\n              maxlength=\"64\"\r\n            />\r\n          </el-form-item>\r\n          <el-form-item\r\n            class=\"icdforminterval\"\r\n            prop=\"dialoglocalname\"\r\n            :label=\"$t('Configuration.VisitPlace.LocalName')\"\r\n          >\r\n            <el-input\r\n              v-model=\"Dialog.dialoglocalname\"\r\n              v-input-filter:common\r\n              maxlength=\"64\"\r\n            />\r\n          </el-form-item>\r\n          <el-form-item\r\n            class=\"icdforminterval\"\r\n            :label=\"$t('Management.Visitor.CountryorRegion')\"\r\n          >\r\n            <el-select\r\n              v-model=\"Dialog.dialogNationCode\"\r\n              :placeholder=\"$t('Configuration.VisitPlace.SelectNationTip')\"\r\n              class=\"full-width\"\r\n            >\r\n              <el-option\r\n                v-for=\"item in Dialog.dialogNation\"\r\n                :key=\"item.key\"\r\n                :label=\"item.label\"\r\n                :value=\"item.value\"\r\n              />\r\n            </el-select>\r\n          </el-form-item>\r\n          <el-form-item\r\n            class=\"icdforminterval\"\r\n            prop=\"dialogTimezone\"\r\n            :label=\"$t('Configuration.VisitPlace.TimeZone')\"\r\n          >\r\n            <el-select\r\n              v-model=\"Dialog.dialogZone\"\r\n              :placeholder=\"$t('Configuration.VisitPlace.SelectTimeZone')\"\r\n              class=\"full-width\"\r\n            >\r\n              <el-option\r\n                v-for=\"item in Dialog.dialogTimeZone\"\r\n                :key=\"item.Name\"\r\n                :label=\"item.Name\"\r\n                :value=\"item.Name\"\r\n              />\r\n            </el-select>\r\n          </el-form-item>\r\n          <el-form-item\r\n            class=\"icdforminterval\"\r\n            prop=\"dialogAddressEN\"\r\n            :label=\"$t('Configuration.VisitPlace.AddressEN')\"\r\n          >\r\n            <el-input\r\n              v-model=\"Dialog.dialogAddressEN\"\r\n              v-input-filter:common\r\n              maxlength=\"250\"\r\n            />\r\n          </el-form-item>\r\n          <el-form-item\r\n            class=\"icdforminterval\"\r\n            prop=\"dialogAddressCN\"\r\n            :label=\"$t('Configuration.VisitPlace.AddressCN')\"\r\n          >\r\n            <el-input\r\n              v-model=\"Dialog.dialogAddressCN\"\r\n              v-input-filter:common\r\n              maxlength=\"250\"\r\n            />\r\n          </el-form-item>\r\n          <el-divider />\r\n          <el-form-item\r\n            class=\"icdforminterval\"\r\n            :label=\"$t('Configuration.VisitPlace.SMSEnable')\"\r\n          >\r\n            <el-switch v-model=\"Dialog.dialogMessageEnable\" />\r\n          </el-form-item>\r\n          <el-form-item\r\n            class=\"icdforminterval\"\r\n            :rules=\"[\r\n              {\r\n                required: Dialog.dialogMessageEnable,\r\n                message: this.$t('Configuration.VisiPlace.TipSMSServiceEmpty'),\r\n                trigger: 'blur',\r\n              },\r\n            ]\"\r\n            prop=\"dialogMessageService\"\r\n            :label=\"$t('Configuration.VisitPlace.SMSServiceName')\"\r\n          >\r\n            <el-select\r\n              v-model=\"Dialog.dialogMessageService\"\r\n              style=\"width: 63%\"\r\n              :disabled=\"!Dialog.dialogMessageEnable\"\r\n            >\r\n              <el-option\r\n                v-for=\"item in Dialog.dialogSMSService\"\r\n                :key=\"item.key\"\r\n                :label=\"item.label\"\r\n                :value=\"item.value\"\r\n              />\r\n            </el-select>\r\n            <span>\r\n              <el-button\r\n                type=\"text\"\r\n                style=\"margin-left: 2%\"\r\n                @click=\"CreateMessage(1)\"\r\n              >\r\n                {{ $t(\"Configuration.VisitPlace.CreateSMSService\") }}\r\n              </el-button>\r\n            </span>\r\n          </el-form-item>\r\n          <el-form-item\r\n            class=\"icdforminterval\"\r\n            :rules=\"[\r\n              {\r\n                required: Dialog.dialogMessageEnable,\r\n                message: this.$t(\r\n                  'Configuration.VisiPlace.TipSMSTemplateGroupEmpty'\r\n                ),\r\n                trigger: 'blur',\r\n              },\r\n            ]\"\r\n            prop=\"dialogMessageTemplate\"\r\n            :label=\"$t('Configuration.VisitPlace.SMSTemplateGroupName')\"\r\n          >\r\n            <el-select\r\n              v-model=\"Dialog.dialogMessageTemplate\"\r\n              style=\"width: 63%\"\r\n              :disabled=\"!Dialog.dialogMessageEnable\"\r\n            >\r\n              <el-option\r\n                v-for=\"item in Dialog.dialogSMSTemGroup\"\r\n                :key=\"item.key\"\r\n                :label=\"item.label\"\r\n                :value=\"item.value\"\r\n              />\r\n            </el-select>\r\n            <span>\r\n              <el-button\r\n                type=\"text\"\r\n                style=\"margin-left: 2%\"\r\n                @click=\"CreateMessage(2)\"\r\n              >\r\n                {{ $t(\"Configuration.VisitPlace.CreateSMSTemplate\") }}\r\n              </el-button>\r\n            </span>\r\n            <span>\r\n              <el-button\r\n                type=\"text\"\r\n                style=\"margin-left: 65%\"\r\n                @click=\"CreateMessage(3)\"\r\n              >\r\n                {{ $t(\"Configuration.VisitPlace.CreateSMSTempalteGroup\") }}\r\n              </el-button>\r\n            </span>\r\n          </el-form-item>\r\n          <el-divider />\r\n          <el-form-item\r\n            class=\"icdforminterval\"\r\n            :label=\"$t('Configuration.VisitPlace.EmailEnable')\"\r\n          >\r\n            <el-switch v-model=\"Dialog.dialogEmailEnable\" />\r\n          </el-form-item>\r\n          <el-form-item\r\n            class=\"icdforminterval\"\r\n            :rules=\"[\r\n              {\r\n                required: Dialog.dialogEmailEnable,\r\n                message: $t('Configuration.VisiPlace.TipEmailServiceEmpty'),\r\n                trigger: 'blur',\r\n              },\r\n            ]\"\r\n            prop=\"dialogEmailService\"\r\n            :label=\"$t('Configuration.VisitPlace.EmailAccountName')\"\r\n          >\r\n            <el-select\r\n              v-model=\"Dialog.dialogEmailService\"\r\n              style=\"width: 63%\"\r\n              :disabled=\"!Dialog.dialogEmailEnable\"\r\n            >\r\n              <el-option\r\n                v-for=\"item in Dialog.dialogEmailAccount\"\r\n                :key=\"item.key\"\r\n                :label=\"item.label\"\r\n                :value=\"item.value\"\r\n              />\r\n            </el-select>\r\n            <span>\r\n              <el-button\r\n                type=\"text\"\r\n                style=\"margin-left: 2%\"\r\n                @click=\"CreateEmailDialog(1)\"\r\n              >\r\n                {{ $t(\"Configuration.VisitPlace.CreateEmailService\") }}\r\n              </el-button>\r\n            </span>\r\n          </el-form-item>\r\n          <el-form-item\r\n            class=\"icdforminterval\"\r\n            :rules=\"[\r\n              {\r\n                required: Dialog.dialogEmailEnable,\r\n                message: $t(\r\n                  'Configuration.VisiPlace.TipEmailTemplaetGroupEmpty'\r\n                ),\r\n                trigger: 'blur',\r\n              },\r\n            ]\"\r\n            prop=\"dialogEmailTemplate\"\r\n            :label=\"$t('Configuration.VisitPlace.EmailTemplateGroupName')\"\r\n          >\r\n            <el-select\r\n              v-model=\"Dialog.dialogEmailTemplate\"\r\n              style=\"width: 63%\"\r\n              :disabled=\"!Dialog.dialogEmailEnable\"\r\n            >\r\n              <el-option\r\n                v-for=\"item in Dialog.dialogEmailTemGroup\"\r\n                :key=\"item.key\"\r\n                :label=\"item.label\"\r\n                :value=\"item.value\"\r\n              />\r\n            </el-select>\r\n            <span>\r\n              <el-button\r\n                type=\"text\"\r\n                style=\"margin-left: 2%\"\r\n                @click=\"CreateEmailDialog(2)\"\r\n              >\r\n                {{ $t(\"Configuration.VisitPlace.CreateEmailTemplate\") }}\r\n              </el-button>\r\n            </span>\r\n            <span>\r\n              <el-button\r\n                type=\"text\"\r\n                style=\"margin-left: 65%\"\r\n                @click=\"CreateEmailDialog(3)\"\r\n              >\r\n                {{ $t(\"Configuration.VisitPlace.CreateEmailTempalteGroup\") }}\r\n              </el-button>\r\n            </span>\r\n          </el-form-item>\r\n          <el-form-item label-width=\"80%\" class=\"icdforminterval\">\r\n            <el-button\r\n              :loading=\"Dialog.dialogSaveLoading\"\r\n              type=\"primary\"\r\n              style=\"width: 8rem\"\r\n              @click=\"DialogClickSubmit\"\r\n            >\r\n              {{ $t(\"Configuration.Save\") }}\r\n            </el-button>\r\n          </el-form-item>\r\n        </el-form>\r\n      </div>\r\n    </el-dialog>\r\n\r\n    <!-- Message Service -->\r\n    <el-dialog\r\n      class=\"create-message-service-dialog\"\r\n      :title=\"$t('Configuration.SMS.EditService')\"\r\n      :visible=\"Message.SMSServiceVisible\"\r\n      :close-on-click-modal=\"false\"\r\n      @close=\"CloseSMSDlg(1)\"\r\n    >\r\n      <div>\r\n        <template>\r\n          <message-service\r\n            ref=\"createsms\"\r\n            class=\"create-message-account\"\r\n            @formdata=\"CreateSMSService\"\r\n          />\r\n        </template>\r\n      </div>\r\n    </el-dialog>\r\n\r\n    <!-- Message Template -->\r\n    <el-dialog\r\n      class=\"create-message-template-dialog\"\r\n      :title=\"$t('Configuration.SMS.EditTemplate')\"\r\n      :visible=\"Message.SMSTemplateVisible\"\r\n      :close-on-click-modal=\"false\"\r\n      @close=\"CloseSMSDlg(2)\"\r\n    >\r\n      <div>\r\n        <template>\r\n          <message-template\r\n            ref=\"createtemplate\"\r\n            class=\"create-message-template\"\r\n            @temformdata=\"CreateSMSTemplate\"\r\n          />\r\n        </template>\r\n      </div>\r\n    </el-dialog>\r\n\r\n    <!-- Message Templaet Group -->\r\n    <el-dialog\r\n      class=\"create-message-template-group-dialog\"\r\n      :title=\"$t('Configuration.SMS.EditTemplateGroup')\"\r\n      :visible=\"Message.SMSTemplateGroupVisible\"\r\n      :close-on-click-modal=\"false\"\r\n      @close=\"CloseSMSDlg(3)\"\r\n    >\r\n      <div>\r\n        <template>\r\n          <message-template-group\r\n            ref=\"createtemplategroup\"\r\n            class=\"create-message-template-group\"\r\n            @temgroupdata=\"CreateSMSTemplateGroup\"\r\n          />\r\n        </template>\r\n      </div>\r\n    </el-dialog>\r\n\r\n    <!-- 新建邮件服务 -->\r\n    <el-dialog\r\n      class=\"aemail-service-dialog\"\r\n      :title=\"$t('Configuration.Email.EditEmailService')\"\r\n      :visible=\"Email.EmailServiceDlg\"\r\n      :close-on-click-modal=\"false\"\r\n      @close=\"CloseEmailDlg(1)\"\r\n    >\r\n      <div>\r\n        <template>\r\n          <email-account\r\n            ref=\"emailaccount\"\r\n            class=\"create-email-account\"\r\n            @emailservicedata=\"CreateEmailAccount\"\r\n          />\r\n        </template>\r\n      </div>\r\n    </el-dialog>\r\n\r\n    <!-- 新建邮件模板 -->\r\n    <el-dialog\r\n      class=\"email-template-dialog\"\r\n      :title=\"$t('Configuration.Email.EditEmailTemplate')\"\r\n      :visible=\"Email.EmailTemplaetDlg\"\r\n      :close-on-click-modal=\"false\"\r\n      @close=\"CloseEmailDlg(2)\"\r\n    >\r\n      <div>\r\n        <template>\r\n          <email-template\r\n            ref=\"emailtemplate\"\r\n            class=\"create-email-template\"\r\n            @emailtemplatedata=\"CreateEmailTemplaet\"\r\n          />\r\n        </template>\r\n      </div>\r\n    </el-dialog>\r\n\r\n    <!-- 新建邮件模板组 -->\r\n    <el-dialog\r\n      class=\"email-template-dialog\"\r\n      :title=\"$t('Configuration.Email.EditEmailTemplateGroup')\"\r\n      :visible=\"Email.EmailTemplateGroupDlg\"\r\n      :close-on-click-modal=\"false\"\r\n      @close=\"CloseEmailDlg(3)\"\r\n    >\r\n      <div>\r\n        <template>\r\n          <email-template-group\r\n            ref=\"emailtemplategroup\"\r\n            class=\"create-email-templategroup\"\r\n            @emailtemplategroupdata=\"CreateEmailTemplaetGroup\"\r\n          />\r\n        </template>\r\n      </div>\r\n    </el-dialog>\r\n  </div>\r\n</template>\r\n\r\n<script>\r\nimport { mapGetters } from \"vuex\";\r\nimport i18n from \"@/languages\";\r\nexport default {\r\n  name: \"Visitplace\",\r\n  components: {},\r\n  data() {\r\n    const ValidateAll = (rule, value, callback) => {\r\n      if (!value) {\r\n        value = \"\";\r\n      }\r\n      if (rule.field === \"dialogbranch\") {\r\n        if (value.length < 1) {\r\n          callback(new Error(i18n.t(\"EmptyTip\")));\r\n        } else if (value.length > 12) {\r\n          callback(new Error(i18n.t(\"Configuration.VisitPlace.TipBranchLong\")));\r\n        } else {\r\n          if (value.search(/[\\W]/g) !== -1) {\r\n            callback(new Error(i18n.t(\"Configuration.BranchFormatError\")));\r\n          }\r\n          callback();\r\n        }\r\n      }\r\n      if (rule.field === \"dialogenname\") {\r\n        if (value.length < 1) {\r\n          callback(new Error(i18n.t(\"EmptyTip\")));\r\n        } else {\r\n          callback();\r\n        }\r\n      }\r\n      if (rule.field === \"dialogAddressCN\") {\r\n        callback();\r\n      }\r\n      if (rule.field === \"dialogAddressEN\") {\r\n        callback();\r\n      }\r\n    };\r\n    return {\r\n      tableData: [],\r\n      TableLoading: false,\r\n      BranchCodeReadOnly: false,\r\n      VisitPlacerules: {\r\n        dialogbranch: [\r\n          { required: true, trigger: \"blur\", validator: ValidateAll },\r\n        ],\r\n        dialogenname: [\r\n          { required: true, trigger: \"blur\", validator: ValidateAll },\r\n        ],\r\n      },\r\n      Dialog: {\r\n        editDlgVisible: false,\r\n        DlgLoading: false,\r\n        dialogbranch: \"\",\r\n        dialoglocalname: \"\",\r\n        dialogenname: \"\",\r\n        dialogAddressCN: \"\",\r\n        dialogAddressEN: \"\",\r\n        dialogMessageEnable: false,\r\n        dialogMessageService: \"\",\r\n        dialogMessageTemplate: \"\",\r\n        dialogEmailEnable: false,\r\n        dialogEmailService: \"\",\r\n        dialogEmailTemplate: \"\",\r\n        dialogSaveLoading: false,\r\n        dialogSMSService: [],\r\n        dialogSMSTemGroup: [],\r\n        dialogEmailAccount: [],\r\n        dialogEmailTemGroup: [],\r\n        dialogNation: [],\r\n        dialogNationCode: \"\",\r\n        dialogTimeZone: [],\r\n        dialogZone: \"\",\r\n      },\r\n      Message: {\r\n        SMSServiceVisible: false,\r\n        SMSTemplateVisible: false,\r\n        SMSTemplateGroupVisible: false,\r\n      },\r\n      Email: {\r\n        EmailServiceDlg: false,\r\n        EmailTemplaetDlg: false,\r\n        EmailTemplateGroupDlg: false,\r\n      },\r\n      RightsCreate: true,\r\n      RightsUpdate: true,\r\n      RightsDelete: true,\r\n    };\r\n  },\r\n  computed: {\r\n    ...mapGetters([\"userrights\", \"language\"]),\r\n  },\r\n  created() {\r\n    this.FetchDta();\r\n  },\r\n  methods: {\r\n    FetchDta() {\r\n      // todo 如果未获取到应不显示\r\n    },\r\n    /**\r\n     * 编辑来访地点\r\n     */\r\n    VisitPlaceEdit(row) {},\r\n    /**\r\n     * 删除来访地点\r\n     */\r\n    VisitPlaceDelete(row) {},\r\n    /**\r\n     * 新建来访地点\r\n     */\r\n    VisitPlaceAddNew() {},\r\n    HandleDialogClose() {\r\n      this.Dialog.dialogbranch = \"\";\r\n      this.Dialog.dialogenname = \"\";\r\n      this.Dialog.dialoglocalname = \"\";\r\n      this.Dialog.dialogSMSService = [];\r\n      this.Dialog.dialogSMSTemGroup = [];\r\n      this.Dialog.dialogEmailAccount = [];\r\n      this.Dialog.dialogEmailTemGroup = [];\r\n      this.Dialog.dialogEmailService = \"\";\r\n      this.Dialog.dialogEmailTemplate = \"\";\r\n      this.Dialog.dialogMessageService = \"\";\r\n      this.Dialog.dialogMessageTemplate = \"\";\r\n      this.Dialog.dialogEmailEnable = false;\r\n      this.Dialog.dialogMessageEnable = false;\r\n      this.Dialog.dialogNationCode = \"\";\r\n      this.Dialog.dialogZone = \"\";\r\n      this.$refs.Dialog.resetFields();\r\n    },\r\n    /**\r\n     * 提交保存\r\n     */\r\n    DialogClickSubmit() {},\r\n    /**\r\n     * 获取所有数据\r\n     */\r\n    GetAllTemplate() {},\r\n    // 新建SMS\r\n    CreateMessage(data) {\r\n      // 新建短信服务 打开对应的dlg\r\n    },\r\n    CloseSMSDlg(data) {\r\n      // 关闭dlg\r\n    },\r\n    CreateSMSService(data) {},\r\n    CreateSMSTemplate(data) {},\r\n    CreateSMSTemplateGroup(data) {},\r\n\r\n    // 邮件\r\n    CreateEmailDialog(data) {},\r\n    // 关闭dialog\r\n    CloseEmailDlg(data) {},\r\n    CreateEmailAccount(data) {},\r\n    CreateEmailTemplaet(data) {},\r\n    CreateEmailTemplaetGroup(data) {},\r\n    /**\r\n     * 获取国家/地区\r\n     */\r\n    GetNation() {},\r\n    /**\r\n     * 获取时区\r\n     */\r\n    GetTimeZone() {},\r\n  },\r\n};\r\n</script>\r\n\r\n<style lang=\"scss\" scoped>\r\n.configuration-visitplace-container {\r\n  width: 100%;\r\n  padding-top: 3px;\r\n  min-height: calc(100vh - 50px);\r\n}\r\n.visit-place {\r\n  .user-configuration-Info {\r\n    width: 75%;\r\n    margin-left: 13%;\r\n    .message-configuration-info,\r\n    .email-configuration-info {\r\n      border: 1px solid #dcdfe6;\r\n      border-spacing: 2px;\r\n      padding: 4px 8px;\r\n      .title {\r\n        text-align: center;\r\n        color: #99a9bf;\r\n        font-size: 1rem;\r\n        width: 100%;\r\n        border-bottom: 1px solid #dcdfe6;\r\n        height: 35px;\r\n        line-height: 35px;\r\n      }\r\n      .message-info,\r\n      .email-info {\r\n        padding: 1rem 0;\r\n        height: 8rem;\r\n        box-sizing: border-box;\r\n        text-align: left;\r\n      }\r\n    }\r\n    .email-configuration-info {\r\n      border-left: 0px;\r\n    }\r\n  }\r\n}\r\n.editvisitplace-dialog {\r\n  .create-visitplace {\r\n    padding: 2rem;\r\n    width: 100%;\r\n    text-align: left;\r\n  }\r\n}\r\n</style>\r\n\r\n"
        }
    ]
}